CHANGELOG.txt
MANIFEST.in
README.in
README.txt
TODO.txt
setup.cfg
setup.py
TurboFeeds.egg-info/PKG-INFO
TurboFeeds.egg-info/SOURCES.txt
TurboFeeds.egg-info/dependency_links.txt
TurboFeeds.egg-info/entry_points.txt
TurboFeeds.egg-info/not-zip-safe
TurboFeeds.egg-info/requires.txt
TurboFeeds.egg-info/top_level.txt
doc/index.html
doc/rest.css
doc/api/api-objects.txt
doc/api/class-tree.html
doc/api/crarr.png
doc/api/epydoc.css
doc/api/epydoc.js
doc/api/help.html
doc/api/identifier-index.html
doc/api/index.html
doc/api/module-tree.html
doc/api/redirect.html
doc/api/turbofeeds-module.html
doc/api/turbofeeds-pysrc.html
doc/api/turbofeeds.controllers-module.html
doc/api/turbofeeds.controllers-pysrc.html
doc/api/turbofeeds.controllers.FeedController-class.html
doc/api/turbofeeds.release-module.html
doc/api/turbofeeds.release-pysrc.html
doc/api/turbofeeds.templates-module.html
doc/api/turbofeeds.templates-pysrc.html
doc/api/turbofeeds.util-module.html
doc/api/turbofeeds.util-pysrc.html
doc/api/turbofeeds.widgets-module.html
doc/api/turbofeeds.widgets-pysrc.html
doc/api/turbofeeds.widgets.FeedButton-class.html
doc/api/turbofeeds.widgets.FeedButton.template_c-class.html
doc/api/turbofeeds.widgets.FeedHeadLinks-class.html
doc/api/turbofeeds.widgets.FeedHeadLinks.template_c-class.html
doc/api/turbofeeds.widgets.FeedLinks-class.html
doc/api/turbofeeds.widgets.FeedLinks.template_c-class.html
doc/api/turbofeeds.widgets.FeedLinksDesc-class.html
doc/api/turbofeeds.widgets.FeedLinksDesc.template_c-class.html
doc/api/turbogears.widgets.base.MetaDescription-class.html
doc/api/turbogears.widgets.meta.MetaWidget-class.html
tools/make_readme.py
tools/make_release.sh
tools/upload.sh
turbofeeds/__init__.py
turbofeeds/controllers.py
turbofeeds/release.py
turbofeeds/util.py
turbofeeds/widgets.py
turbofeeds/static/.DS_Store
turbofeeds/static/css/feeds.css
turbofeeds/static/images/feed-icon-14x14.png
turbofeeds/static/images/feed-icon-28x28.png
turbofeeds/templates/__init__.py
turbofeeds/templates/atom0_3.html
turbofeeds/templates/atom0_3.kid
turbofeeds/templates/atom1_0.html
turbofeeds/templates/atom1_0.kid
turbofeeds/templates/mrss1_1_1.html
turbofeeds/templates/mrss1_1_1.kid
turbofeeds/templates/rss2_0.html
