Metadata-Version: 1.0
Name: TurboFeeds
Version: 0.2b
Summary: TurboGears controller and widgets for feed handling.
Home-page: http://chrisarndt.de/projects/turbofeeds
Author: Christopher Arndt
Author-email: chris@chrisarndt.de
License: MIT license
Download-URL: http://cheeseshop.python.org/pypi/TurboFeeds
Keywords: turbogears.widgets
Platform: UNKNOWN
Classifier: Development Status :: 4 - Beta
Classifier: Operating System :: OS Independent
Classifier: Programming Language :: Python
Classifier: Topic :: Software Development :: Libraries :: Python Modules
Classifier: Framework :: TurboGears
Classifier: Framework :: TurboGears :: Widgets
